rv32i_mono/src/bru.sv
module bru (
    input logic [31:0] ru_rs1,
    input logic [31:0] ru_rs2,
    input logic [4:0] brOp,
    output logic nextPCSrc
);

  always_comb begin
    case (brOp)
      5'b00000: nextPCSrc = 1'b0; // No branch
      5'b10000: nextPCSrc = 1'b1; // JAL/JALR - Salto incondicional
      5'b01000: nextPCSrc = (ru_rs1 == ru_rs2) ? 1'b1 : 1'b0; // BEQ
      5'b01001: nextPCSrc = (ru_rs1 != ru_rs2) ? 1'b1 : 1'b0; // BNE
      5'b01100: nextPCSrc = ($signed(ru_rs1) < $signed(ru_rs2)) ? 1'b1 : 1'b0; // BLT
      5'b01101: nextPCSrc = ($signed(ru_rs1) >= $signed(ru_rs2)) ? 1'b1 : 1'b0; // BGE
      5'b01110: nextPCSrc = (ru_rs1 < ru_rs2) ? 1'b1 : 1'b0; // BLTU
      5'b01111: nextPCSrc = (ru_rs1 >= ru_rs2) ? 1'b1 : 1'b0; // BGEU
      default: nextPCSrc = 1'b0; // Valor por defecto (no debería ocurrir)
    endcase
  end
endmodule

rv32i_mono/tb/bru_tb.sv
module bru_tb;
  // Señales internas
  logic [31:0] ru_rs1;
  logic [31:0] ru_rs2;
  logic [4:0] brOp;
  logic nextPCSrc;

  // Instancia del módulo bru
  bru uut (
    .ru_rs1(ru_rs1),
    .ru_rs2(ru_rs2),
    .brOp(brOp),
    .nextPCSrc(nextPCSrc)
  );

  initial begin
    $dumpfile("vcd/bru_tb.vcd");
    $dumpvars(0, bru_tb);
    $display("=================================================================");
    $display("            TESTBENCH PARA BRANCH UNIT (BRU)");
    $display("=================================================================\n");

    // -----------------------------------------------------------
    // Prueba 0: BEQ - Igualdad (caso negativo)
    // ru_rs1 = 10, ru_rs2 = 20, brOp = 01000 (BEQ)
    // -----------------------------------------------------------
    ru_rs1 = 32'd10;
    ru_rs2 = 32'd20;
    brOp = 5'b01000; // BEQ
    #10;
    $display("BEQ Test (negativo): ru_rs1 = %d, ru_rs2 = %d, nextPCSrc = %b (debe ser 0)", ru_rs1, ru_rs2, nextPCSrc);

    // -----------------------------------------------------------
    // Prueba 1: BEQ - Igualdad
    // ru_rs1 = 10, ru_rs2 = 10, brOp = 01000 (BEQ)
    // -----------------------------------------------------------
    ru_rs1 = 32'd10;
    ru_rs2 = 32'd10;
    brOp = 5'b01000; // BEQ
    #10;
    $display("BEQ Test: ru_rs1 = %d, ru_rs2 = %d, nextPCSrc = %b (debe ser 1)", ru_rs1, ru_rs2, nextPCSrc);

    // -----------------------------------------------------------
    // Prueba 2: BNE - Desigualdad
    // ru_rs1 = 15, ru_rs2 = 20, brOp = 01001 (BNE)
    // -----------------------------------------------------------
    ru_rs1 = 32'd15;
    ru_rs2 = 32'd20;
    brOp = 5'b01001; // BNE
    #10;
    $display("BNE Test: ru_rs1 = %d, ru_rs2 = %d, nextPCSrc = %b (debe ser 1)", ru_rs1, ru_rs2, nextPCSrc);

    // -----------------------------------------------------------
    // Prueba 3: BLT - Menor que (signed)
    // ru_rs1 = -5, ru_rs2 = 10, brOp = 01100 (BLT)
    // -----------------------------------------------------------
    ru_rs1 = -32'sd5;
    ru_rs2 = 32'd10;
    brOp = 5'b01100; // BLT
    #10;
    $display("BLT Test: ru_rs1 = %d, ru_rs2 = %d, nextPCSrc = %b (debe ser 1)", ru_rs1, ru_rs2, nextPCSrc);

    // -----------------------------------------------------------
    // Prueba 4: BGE - Mayor o igual que (signed)
    // ru_rs1 = 10, ru_rs2 = 10, brOp = 01101 (BGE)
    // -----------------------------------------------------------
    ru_rs1 = 32'd10;
    ru_rs2 = 32'd10;
    brOp = 5'b01101; // BGE
    #10;
    $display("BGE Test: ru_rs1 = %d, ru_rs2 = %d, nextPCSrc = %b (debe ser 1)", ru_rs1, ru_rs2, nextPCSrc);

    // -----------------------------------------------------------
    // Prueba 5: BLTU - Menor que (unsigned)
    // ru_rs1 = 5, ru_rs2 = 10, brOp = 01110 (BLTU)
    // -----------------------------------------------------------
    ru_rs1 = 32'd5;
    ru_rs2 = 32'd10;
    brOp = 5'b01110; // BLTU
    #10;
    $display("BLTU Test: ru_rs1 = %d, ru_rs2 = %d, nextPCSrc = %b (debe ser 1)", ru_rs1, ru_rs2, nextPCSrc);
    // -----------------------------------------------------------
    // Prueba 6: BGEU - Mayor o igual que (unsigned)
    // ru_rs1 = 20, ru_rs2 = 10, brOp = 01111 (BGEU)
    // -----------------------------------------------------------
    ru_rs1 = 32'd20;
    ru_rs2 = 32'd10;
    brOp = 5'b01111; // BGEU
    #10;
    $display("BGEU Test: ru_rs1 = %d, ru_rs2 = %d, nextPCSrc = %b (debe ser 1)", ru_rs1, ru_rs2, nextPCSrc);

    // -----------------------------------------------------------
    // Prueba 7: desde el Program counter (sin branch)
    // ru_rs1 = 0, ru_rs2 = 0, brOp = 00000 (No branch)
    // -----------------------------------------------------------
    ru_rs1 = 32'd0;
    ru_rs2 = 32'd0;
    brOp = 5'b00000; // No branch
    #10;
    $display("No Branch Test: ru_rs1 = %d, ru_rs2 = %d, nextPCSrc = %b (debe ser 0)", ru_rs1, ru_rs2, nextPCSrc);

    $display("\n=================================================================");
    $display("                     FIN DE SIMULACIÓN");
    $display("=================================================================");
    #20 $finish;
  end
endmodule

rv32i_mono/vcd/bru_tb.vcd
$date
	Tue Nov 25 15:52:49 2025
$end
$version
	Icarus Verilog
$end
$timescale
	1s
$end
$scope module bru_tb $end
$var wire 1 ! nextPCSrc $end
$var reg 5 " brOp [4:0] $end
$var reg 32 # ru_rs1 [31:0] $end
$var reg 32 $ ru_rs2 [31:0] $end
$scope module uut $end
$var wire 5 % brOp [4:0] $end
$var wire 32 & ru_rs1 [31:0] $end
$var wire 32 ' ru_rs2 [31:0] $end
$var reg 1 ! nextPCSrc $end
$upscope $end
$upscope $end
$enddefinitions $end
$comment Show the parameter values. $end
$dumpall
$end
#0
$dumpvars
b10100 '
b1010 &
b1000 %
b10100 $
b1010 #
b1000 "
0!
$end
#10
1!
b1010 $
b1010 '
#20
b1001 "
b1001 %
b10100 $
b10100 '
b1111 #
b1111 &
#30
b1100 "
b1100 %
b1010 $
b1010 '
b11111111111111111111111111111011 #
b11111111111111111111111111111011 &
#40
b1101 "
b1101 %
b1010 #
b1010 &
#50
b1110 "
b1110 %
b101 #
b101 &
#60
b1111 "
b1111 %
b10100 #
b10100 &
#70
0!
b0 "
b0 %
b0 $
b0 '
b0 #
b0 &
