rv32i_mono/src/debouncer.sv
module debouncer #(
    parameter DEBOUNCE_TIME = 20'd1_000_000  // ~20ms a 50MHz
)(
    input  logic clk,
    input  logic rst,
    input  logic button_in,
    output logic button_out
);

    logic [19:0] counter;
    logic button_sync_0, button_sync_1;

    // Sincronizador de dos flip-flops para evitar metaestabilidad
    always_ff @(posedge clk or posedge rst) begin
        if (rst) begin
            button_sync_0 <= 1'b1;  // Botones activos en bajo en DE1-SoC
            button_sync_1 <= 1'b1;
        end else begin
            button_sync_0 <= button_in;
            button_sync_1 <= button_sync_0;
        end
    end

    // Lógica de debounce
    always_ff @(posedge clk or posedge rst) begin
        if (rst) begin
            counter <= 20'd0;
            button_out <= 1'b1;
        end else begin
            if (button_sync_1 == button_out) begin
                // Estado estable
                counter <= 20'd0;
            end else begin
                // Estado inestable
                counter <= counter + 20'd1;
                if (counter >= DEBOUNCE_TIME) begin
                    button_out <= button_sync_1;
                    counter <= 20'd0;
                end
            end
        end
    end

endmodule

rv32i_mono/tb/debouncer_tb.sv
`timescale 1ns/1ps

module debouncer_tb;

    logic clk;
    logic rst;
    logic button_in;
    logic button_out;

    // Instancia del DUT
    debouncer #(
        .DEBOUNCE_TIME(100)  // Valor pequeño para simulación rápida
    ) dut (
        .clk(clk),
        .rst(rst),
        .button_in(button_in),
        .button_out(button_out)
    );

    // Generador de clock (50 MHz = 20ns periodo)
    initial begin
        clk = 0;
        forever #10 clk = ~clk;
    end

    // Estímulos
    initial begin
        $dumpfile("vcd/debouncer_tb.vcd");
        $dumpvars(0, debouncer_tb);

        // Inicialización
        rst = 1;
        button_in = 1;  // Botón no presionado (activo bajo)
        #50;
        rst = 0;
        #100;

        $display("=== Test 1: Botón presionado sin rebotes ===");
        button_in = 0;  // Presionar botón
        #3000;
        button_in = 1;  // Soltar botón
        #3000;

        $display("=== Test 2: Botón con rebotes ===");
        // Simular rebotes al presionar
        button_in = 0;
        #40;
        button_in = 1;
        #20;
        button_in = 0;
        #30;
        button_in = 1;
        #15;
        button_in = 0;  // Finalmente estable
        #3000;

        // Simular rebotes al soltar
        button_in = 1;
        #40;
        button_in = 0;
        #20;
        button_in = 1;
        #30;
        button_in = 0;
        #15;
        button_in = 1;  // Finalmente estable
        #3000;

        $display("=== Test 3: Pulsos muy cortos (ignorados) ===");
        button_in = 0;
        #30;  // Muy corto, debería ser ignorado
        button_in = 1;
        #3000;

        $display("=== Simulación completada ===");
        $finish;
    end

    // Monitor
    initial begin
        $monitor("Time=%0t rst=%b button_in=%b button_out=%b", 
                 $time, rst, button_in, button_out);
    end

endmodule

rv32i_mono/vcd/debouncer_tb.vcd
$date
	Tue Nov 25 16:09:22 2025
$end
$version
	Icarus Verilog
$end
$timescale
	1ps
$end
$scope module debouncer_tb $end
$var wire 1 ! button_out $end
$var reg 1 " button_in $end
$var reg 1 # clk $end
$var reg 1 $ rst $end
$scope module dut $end
$var wire 1 " button_in $end
$var wire 1 # clk $end
$var wire 1 $ rst $end
$var parameter 32 % DEBOUNCE_TIME $end
$var reg 1 ! button_out $end
$var reg 1 & button_sync_0 $end
$var reg 1 ' button_sync_1 $end
$var reg 20 ( counter [19:0] $end
$upscope $end
$upscope $end
$enddefinitions $end
$comment Show the parameter values. $end
$dumpall
b1100100 %
$end
#0
$dumpvars
b0 (
1'
1&
1$
0#
1"
1!
$end
#10000
1#
#20000
0#
#30000
1#
#40000
0#
#50000
1#
0$
#60000
0#
#70000
1#
#80000
0#
#90000
1#
#100000
0#
#110000
1#
#120000
0#
#130000
1#
#140000
0#
#150000
0&
1#
0"
#160000
0#
#170000
0'
1#
#180000
0#
#190000
b1 (
1#
#200000
0#
#210000
b10 (
1#
#220000
0#
#230000
b11 (
1#
#240000
0#
#250000
b100 (
1#
#260000
0#
#270000
b101 (
1#
#280000
0#
#290000
b110 (
1#
#300000
0#
#310000
b111 (
1#
#320000
0#
#330000
b1000 (
1#
#340000
0#
#350000
b1001 (
1#
#360000
0#
#370000
b1010 (
1#
#380000
0#
#390000
b1011 (
1#
#400000
0#
#410000
b1100 (
1#
#420000
0#
#430000
b1101 (
1#
#440000
0#
#450000
b1110 (
1#
#460000
0#
#470000
b1111 (
1#
#480000
0#
#490000
b10000 (
1#
#500000
0#
#510000
b10001 (
1#
#520000
0#
#530000
b10010 (
1#
#540000
0#
#550000
b10011 (
1#
#560000
0#
#570000
b10100 (
1#
#580000
0#
#590000
b10101 (
1#
#600000
0#
#610000
b10110 (
1#
#620000
0#
#630000
b10111 (
1#
#640000
0#
#650000
b11000 (
1#
#660000
0#
#670000
b11001 (
1#
#680000
0#
#690000
b11010 (
1#
#700000
0#
#710000
b11011 (
1#
#720000
0#
#730000
b11100 (
1#
#740000
0#
#750000
b11101 (
1#
#760000
0#
#770000
b11110 (
1#
#780000
0#
#790000
b11111 (
1#
#800000
0#
#810000
b100000 (
1#
#820000
0#
#830000
b100001 (
1#
#840000
0#
#850000
b100010 (
1#
#860000
0#
#870000
b100011 (
1#
#880000
0#
#890000
b100100 (
1#
#900000
0#
#910000
b100101 (
1#
#920000
0#
#930000
b100110 (
1#
#940000
0#
#950000
b100111 (
1#
#960000
0#
#970000
b101000 (
1#
#980000
0#
#990000
b101001 (
1#
#1000000
0#
#1010000
b101010 (
1#
#1020000
0#
#1030000
b101011 (
1#
#1040000
0#
#1050000
b101100 (
1#
#1060000
0#
#1070000
b101101 (
1#
#1080000
0#
#1090000
b101110 (
1#
#1100000
0#
#1110000
b101111 (
1#
#1120000
0#
#1130000
b110000 (
1#
#1140000
0#
#1150000
b110001 (
1#
#1160000
0#
#1170000
b110010 (
1#
#1180000
0#
#1190000
b110011 (
1#
#1200000
0#
#1210000
b110100 (
1#
#1220000
0#
#1230000
b110101 (
1#
#1240000
0#
#1250000
b110110 (
1#
#1260000
0#
#1270000
b110111 (
1#
#1280000
0#
#1290000
b111000 (
1#
#1300000
0#
#1310000
b111001 (
1#
#1320000
0#
#1330000
b111010 (
1#
#1340000
0#
#1350000
b111011 (
1#
#1360000
0#
#1370000
b111100 (
1#
#1380000
0#
#1390000
b111101 (
1#
#1400000
0#
#1410000
b111110 (
1#
#1420000
0#
#1430000
b111111 (
1#
#1440000
0#
#1450000
b1000000 (
1#
#1460000
0#
#1470000
b1000001 (
1#
#1480000
0#
#1490000
b1000010 (
1#
#1500000
0#
#1510000
b1000011 (
1#
#1520000
0#
#1530000
b1000100 (
1#
#1540000
0#
#1550000
b1000101 (
1#
#1560000
0#
#1570000
b1000110 (
1#
#1580000
0#
#1590000
b1000111 (
1#
#1600000
0#
#1610000
b1001000 (
1#
#1620000
0#
#1630000
b1001001 (
1#
#1640000
0#
#1650000
b1001010 (
1#
#1660000
0#
#1670000
b1001011 (
1#
#1680000
0#
#1690000
b1001100 (
1#
#1700000
0#
#1710000
b1001101 (
1#
#1720000
0#
#1730000
b1001110 (
1#
#1740000
0#
#1750000
b1001111 (
1#
#1760000
0#
#1770000
b1010000 (
1#
#1780000
0#
#1790000
b1010001 (
1#
#1800000
0#
#1810000
b1010010 (
1#
#1820000
0#
#1830000
b1010011 (
1#
#1840000
0#
#1850000
b1010100 (
1#
#1860000
0#
#1870000
b1010101 (
1#
#1880000
0#
#1890000
b1010110 (
1#
#1900000
0#
#1910000
b1010111 (
1#
#1920000
0#
#1930000
b1011000 (
1#
#1940000
0#
#1950000
b1011001 (
1#
#1960000
0#
#1970000
b1011010 (
1#
#1980000
0#
#1990000
b1011011 (
1#
#2000000
0#
#2010000
b1011100 (
1#
#2020000
0#
#2030000
b1011101 (
1#
#2040000
0#
#2050000
b1011110 (
1#
#2060000
0#
#2070000
b1011111 (
1#
#2080000
0#
#2090000
b1100000 (
1#
#2100000
0#
#2110000
b1100001 (
1#
#2120000
0#
#2130000
b1100010 (
1#
#2140000
0#
#2150000
b1100011 (
1#
#2160000
0#
#2170000
b1100100 (
1#
#2180000
0#
#2190000
0!
b0 (
1#
