rv32i_mono/src/dm.sv
module dm (
    input  logic        clk,        // reloj del sistema
    input  logic        DMWr,       // enable de escritura
    input  logic [2:0]  DMCtrl,     // tipo de acceso
    input  logic [31:0] addr,       // dirección desde la ALU
    input  logic [31:0] DataWr,     // dato a escribir
    output logic [31:0] DataRd,     // dato leído
    output logic [31:0] debug_dm_word [0:7] // debug: primeros 8 words
);

    // Memoria de 1 KiB (1024 bytes) - igual que segmentado
    (* ramstyle = "M10K" *) logic [7:0] mem [0:1023];

    // Inicializar memoria a 0 (compatible con síntesis FPGA)
    integer i;
    initial begin
        for (i = 0; i < 1024; i = i + 1) begin
            mem[i] = 8'h00;
        end
    end

    // Debug: exportar los primeros 8 words como outputs
    genvar dbg_i;
    generate
        for (dbg_i = 0; dbg_i < 8; dbg_i = dbg_i + 1) begin : dm_dbg
            assign debug_dm_word[dbg_i] = {mem[4*dbg_i+3], mem[4*dbg_i+2], mem[4*dbg_i+1], mem[4*dbg_i+0]};
        end
    endgenerate

    // Aliases para lectura (más legible y compatible con Icarus)
    // Limitar direcciones a 10 bits (1024 bytes)
    logic [9:0] addr_limited;
    assign addr_limited = addr[9:0];
    
    logic [7:0] b0, b1, b2, b3;
    assign b0 = mem[addr_limited];
    assign b1 = mem[addr_limited + 1];
    assign b2 = mem[addr_limited + 2];
    assign b3 = mem[addr_limited + 3];

    //========================================================
    // LECTURA COMBINACIONAL (sin reloj)
    //========================================================
    assign DataRd =
        (DMCtrl == 3'b000) ? {{24{b0[7]}}, b0} :                // LB
        (DMCtrl == 3'b001) ? {{16{b1[7]}}, b1, b0} :            // LH
        (DMCtrl == 3'b010) ? {b3, b2, b1, b0} :                 // LW
        (DMCtrl == 3'b100) ? {24'b0, b0} :                      // LBU
        (DMCtrl == 3'b101) ? {16'b0, b1, b0} :                  // LHU
                             32'b0;

    //========================================================
    // ESCRITURA SINCRÓNICA (con reloj)
    //========================================================
    always_ff @(posedge clk) begin
        if (DMWr) begin
            case (DMCtrl)
                3'b000: mem[addr_limited] <= DataWr[7:0];                       // SB
                3'b001: begin                                           // SH
                    mem[addr_limited]     <= DataWr[7:0];
                    mem[addr_limited + 1] <= DataWr[15:8];
                end
                3'b010: begin                                           // SW
                    mem[addr_limited]     <= DataWr[7:0];
                    mem[addr_limited + 1] <= DataWr[15:8];
                    mem[addr_limited + 2] <= DataWr[23:16];
                    mem[addr_limited + 3] <= DataWr[31:24];
                end
            endcase
        end
    end

endmodule

rv32i_mono/tb/dm_tb.sv
`timescale 1ns/1ps

module dm_tb;

    logic clk;
    logic DMWr;
    logic [2:0] DMCtrl;
    logic [31:0] addr, DataWr, DataRd;

    // Instancia de la memoria
    dm uut (
        .clk(clk),
        .DMWr(DMWr),
        .DMCtrl(DMCtrl),
        .addr(addr),
        .DataWr(DataWr),
        .DataRd(DataRd)
    );

    // Generador de reloj (10 ns período)
    initial clk = 0;
    always #5 clk = ~clk;

    // Test sequence
    initial begin
        $dumpfile("vcd/dm_tb.vcd");
        $dumpvars(0, dm_tb);
        $display("=== INICIO TESTBENCH DATA MEMORY ===");

        DMWr = 0; addr = 0; DataWr = 0; DMCtrl = 3'b010;
        #10;

        // --- Store Word (SW) ---
        DMWr = 1;
        DMCtrl = 3'b010;  // SW
        addr = 32'h00000004;
        DataWr = 32'hDEADBEEF;
        @(posedge clk);
        #1;  // Esperar después del flanco
        DMWr = 0;

        // --- Load Word (LW) ---
        #10;
        DMCtrl = 3'b010;  // LW
        addr = 32'h00000004;
        #2 $display("LW  -> DataRd = %h (esperado DEADBEEF)", DataRd);

        // --- Store Byte (SB) ---
        #10;
        DMWr = 1;
        DMCtrl = 3'b000;  // SB
        addr = 32'h00000008;
        DataWr = 32'h000000AA;
        @(posedge clk);
        #1;  // Esperar después del flanco
        DMWr = 0;

        // --- Load Byte (LB) ---
        #10;
        DMCtrl = 3'b000;  // LB (signed)
        addr = 32'h00000008;
        #2 $display("LB  -> DataRd = %h (esperado FFFFFFAA)", DataRd);

        // --- Load Byte Unsigned (LBU) ---
        #10;
        DMCtrl = 3'b100;  // LBU (unsigned)
        addr = 32'h00000008;
        #2 $display("LBU -> DataRd = %h (esperado 000000AA)", DataRd);

        // --- Store Halfword (SH) y Load Halfword Unsigned (LHU) ---
        #10;
        DMWr = 1;
        DMCtrl = 3'b001;  // SH
        addr = 32'h0000000C;
        DataWr = 32'h0000BEEF;
        @(posedge clk);
        #1;  // Esperar después del flanco
        DMWr = 0;

        #10;
        DMCtrl = 3'b101;  // LHU
        addr = 32'h0000000C;
        #2 $display("LHU -> DataRd = %h (esperado 0000BEEF)", DataRd);

        #20;
        $display("=== FIN TESTBENCH ===");
        $finish;
    end
endmodule

rv32i_mono/vcd/dm_tb.vcd
$date
	Tue Nov 25 16:11:35 2025
$end
$version
	Icarus Verilog
$end
$timescale
	1ps
$end
$scope module dm_tb $end
$var wire 32 ! DataRd [31:0] $end
$var reg 3 " DMCtrl [2:0] $end
$var reg 1 # DMWr $end
$var reg 32 $ DataWr [31:0] $end
$var reg 32 % addr [31:0] $end
$var reg 1 & clk $end
$scope module uut $end
$var wire 3 ' DMCtrl [2:0] $end
$var wire 1 # DMWr $end
$var wire 32 ( DataWr [31:0] $end
$var wire 32 ) addr [31:0] $end
$var wire 8 * b0 [7:0] $end
$var wire 8 + b1 [7:0] $end
$var wire 8 , b2 [7:0] $end
$var wire 8 - b3 [7:0] $end
$var wire 1 & clk $end
$var wire 10 . addr_limited [9:0] $end
$var wire 32 / DataRd [31:0] $end
$var integer 32 0 i [31:0] $end
$scope begin dm_dbg[0] $end
$var parameter 2 1 dbg_i $end
$upscope $end
$scope begin dm_dbg[1] $end
$var parameter 2 2 dbg_i $end
$upscope $end
$scope begin dm_dbg[2] $end
$var parameter 3 3 dbg_i $end
$upscope $end
$scope begin dm_dbg[3] $end
$var parameter 3 4 dbg_i $end
$upscope $end
$scope begin dm_dbg[4] $end
$var parameter 4 5 dbg_i $end
$upscope $end
$scope begin dm_dbg[5] $end
$var parameter 4 6 dbg_i $end
$upscope $end
$scope begin dm_dbg[6] $end
$var parameter 4 7 dbg_i $end
$upscope $end
$scope begin dm_dbg[7] $end
$var parameter 4 8 dbg_i $end
$upscope $end
$upscope $end
$upscope $end
$enddefinitions $end
$comment Show the parameter values. $end
$dumpall
b111 8
b110 7
b101 6
b100 5
b11 4
b10 3
b1 2
b0 1
$end
#0
$dumpvars
b10000000000 0
b0 /
b0 .
b0 -
b0 ,
b0 +
b0 *
b0 )
b0 (
b10 '
0&
b0 %
b0 $
0#
b10 "
b0 !
$end
#5000
1&
#10000
b100 .
0&
b11011110101011011011111011101111 $
b11011110101011011011111011101111 (
b100 %
b100 )
1#
#15000
b11011110101011011011111011101111 !
b11011110101011011011111011101111 /
b11011110 -
b10101101 ,
b10111110 +
b11101111 *
1&
#16000
0#
#20000
0&
#25000
1&
#30000
0&
#35000
1&
#38000
b0 *
b0 +
b0 ,
b0 -
b1000 .
b0 !
b0 /
b10101010 $
b10101010 (
b1000 %
b1000 )
b0 "
b0 '
1#
#40000
0&
#45000
b11111111111111111111111110101010 !
b11111111111111111111111110101010 /
b10101010 *
1&
#46000
0#
#50000
0&
#55000
1&
#60000
0&
#65000
1&
#68000
b10101010 !
b10101010 /
b100 "
b100 '
#70000
0&
#75000
1&
#80000
b0 !
b0 /
b0 *
b1100 .
0&
b1011111011101111 $
b1011111011101111 (
b1100 %
b1100 )
b1 "
b1 '
1#
#85000
b11111111111111111011111011101111 !
b11111111111111111011111011101111 /
b10111110 +
b11101111 *
1&
#86000
0#
#90000
0&
#95000
1&
#96000
b1011111011101111 !
b1011111011101111 /
b101 "
b101 '
