rv32i_mono/src/edge_detector.sv
module edge_detector (
    input  logic clk,
    input  logic rst,
    input  logic signal_in,
    output logic edge_detected
);

    logic signal_d;

    always_ff @(posedge clk or posedge rst) begin
        if (rst) begin
            signal_d <= 1'b1;  // Botones activos en bajo
        end else begin
            signal_d <= signal_in;
        end
    end

    // Detectar flanco descendente (presión de botón)
    assign edge_detected = signal_d & ~signal_in;

endmodule

rv32i_mono/tb/edge_detector_tb.sv
`timescale 1ns/1ps

module edge_detector_tb;

    logic clk;
    logic rst;
    logic signal_in;
    logic edge_detected;

    // Instancia del DUT
    edge_detector dut (
        .clk(clk),
        .rst(rst),
        .signal_in(signal_in),
        .edge_detected(edge_detected)
    );

    // Generador de clock
    initial begin
        clk = 0;
        forever #10 clk = ~clk;
    end

    // Estímulos
    initial begin
        $dumpfile("vcd/edge_detector_tb.vcd");
        $dumpvars(0, edge_detector_tb);

        // Inicialización
        rst = 1;
        signal_in = 1;
        #50;
        rst = 0;
        #100;

        $display("=== Test 1: Flanco descendente ===");
        signal_in = 0;  // Flanco descendente
        #20;
        signal_in = 1;
        #100;

        $display("=== Test 2: Múltiples flancos ===");
        signal_in = 0;
        #40;
        signal_in = 1;
        #40;
        signal_in = 0;
        #40;
        signal_in = 1;
        #100;

        $display("=== Test 3: Señal mantenida en bajo ===");
        signal_in = 0;
        #200;  // Debe detectar solo un pulso al inicio
        signal_in = 1;
        #100;

        $display("=== Simulación completada ===");
        $finish;
    end

    // Monitor
    initial begin
        $monitor("Time=%0t rst=%b signal_in=%b edge_detected=%b", 
                 $time, rst, signal_in, edge_detected);
    end

endmodule

rv32i_mono/vcd/edge_detector_tb.vcd
$date
	Tue Nov 25 16:16:31 2025
$end
$version
	Icarus Verilog
$end
$timescale
	1ps
$end
$scope module edge_detector_tb $end
$var wire 1 ! edge_detected $end
$var reg 1 " clk $end
$var reg 1 # rst $end
$var reg 1 $ signal_in $end
$scope module dut $end
$var wire 1 " clk $end
$var wire 1 ! edge_detected $end
$var wire 1 # rst $end
$var wire 1 $ signal_in $end
$var reg 1 % signal_d $end
$upscope $end
$upscope $end
$enddefinitions $end
$comment Show the parameter values. $end
$dumpall
$end
#0
$dumpvars
1%
1$
1#
0"
0!
$end
#10000
1"
#20000
0"
#30000
1"
#40000
0"
#50000
1"
0#
#60000
0"
#70000
1"
#80000
0"
#90000
1"
#100000
0"
#110000
1"
#120000
0"
#130000
1"
#140000
0"
#150000
0%
0!
1"
0$
#160000
0"
#170000
1%
1"
1$
#180000
0"
#190000
1"
#200000
0"
#210000
1"
#220000
0"
#230000
1"
#240000
0"
#250000
1"
#260000
0"
#270000
0%
0!
1"
0$
#280000
0"
#290000
1"
#300000
0"
#310000
1%
1"
1$
#320000
0"
#330000
1"
#340000
0"
#350000
0%
0!
1"
0$
#360000
0"
#370000
1"
#380000
0"
#390000
1%
1"
1$
#400000
0"
#410000
1"
#420000
0"
#430000
1"
#440000
0"
#450000
1"
#460000
0"
#470000
1"
#480000
0"
#490000
0%
0!
1"
0$
#500000
0"
#510000
1"
#520000
0"
#530000
1"
#540000
0"
#550000
1"
#560000
0"
#570000
1"
#580000
0"
#590000
1"
#600000
0"
#610000
1"
#620000
0"
#630000
1"
#640000
0"
#650000
1"
#660000
0"
#670000
1"
#680000
0"
#690000
1%
1"
1$
