rv32i_mono/src/hex_decoder.sv
module hex_decoder(
  input logic [3:0] hex_value,      // Valor hexadecimal de entrada (0-F)
  output logic [6:0] seg            // Salida para segmentos (activo en bajo)
);

  // Decodificación de cada dígito hexadecimal
  // Segmentos:  seg[6:0] = {g, f, e, d, c, b, a}
  //             
  //       a
  //      ---
  //   f |   | b
  //      -g-
  //   e |   | c
  //      ---
  //       d
  
  always_comb begin
    case (hex_value)
      4'h0: seg = 7'b1000000; // 0
      4'h1: seg = 7'b1111001; // 1
      4'h2: seg = 7'b0100100; // 2
      4'h3: seg = 7'b0110000; // 3
      4'h4: seg = 7'b0011001; // 4
      4'h5: seg = 7'b0010010; // 5
      4'h6: seg = 7'b0000010; // 6
      4'h7: seg = 7'b1111000; // 7
      4'h8: seg = 7'b0000000; // 8
      4'h9: seg = 7'b0010000; // 9
      4'hA: seg = 7'b0001000; // A
      4'hB: seg = 7'b0000011; // b
      4'hC: seg = 7'b1000110; // C
      4'hD: seg = 7'b0100001; // d
      4'hE: seg = 7'b0000110; // E
      4'hF: seg = 7'b0001110; // F
      default: seg = 7'b1111111; // Apagado
    endcase
  end

endmodule

rv32i_mono/src/hex_display_6.sv
module hex_display_6 (
    input  logic [23:0] value,          // Valor de 24 bits a mostrar
    output logic [6:0]  hex0,           // Display 0 (LSB)
    output logic [6:0]  hex1,           // Display 1
    output logic [6:0]  hex2,           // Display 2
    output logic [6:0]  hex3,           // Display 3
    output logic [6:0]  hex4,           // Display 4
    output logic [6:0]  hex5            // Display 5 (MSB)
);

    // Instanciar 6 decodificadores hexadecimales
    hex_decoder decoder0 (.hex_value(value[3:0]),   .seg(hex0));
    hex_decoder decoder1 (.hex_value(value[7:4]),   .seg(hex1));
    hex_decoder decoder2 (.hex_value(value[11:8]),  .seg(hex2));
    hex_decoder decoder3 (.hex_value(value[15:12]), .seg(hex3));
    hex_decoder decoder4 (.hex_value(value[19:16]), .seg(hex4));
    hex_decoder decoder5 (.hex_value(value[23:20]), .seg(hex5));

endmodule

rv32i_mono/tb/hex_display_6_tb.sv
`timescale 1ns/1ps

module hex_display_6_tb;

    logic [23:0] value;
    logic [6:0] hex0, hex1, hex2, hex3, hex4, hex5;

    // Instancia del DUT
    hex_display_6 dut (
        .value(value),
        .hex0(hex0),
        .hex1(hex1),
        .hex2(hex2),
        .hex3(hex3),
        .hex4(hex4),
        .hex5(hex5)
    );

    // Estímulos
    initial begin
        $dumpfile("vcd/hex_display_6_tb.vcd");
        $dumpvars(0, hex_display_6_tb);

        $display("=== Test de Hex Display 6 Dígitos ===");
        
        // Test 1: Valor 0
        value = 24'h000000;
        #100;
        $display("Valor: %h => HEX5-0: %h %h %h %h %h %h", 
                 value, hex5, hex4, hex3, hex2, hex1, hex0);

        // Test 2: Valor máximo
        value = 24'hFFFFFF;
        #100;
        $display("Valor: %h => HEX5-0: %h %h %h %h %h %h", 
                 value, hex5, hex4, hex3, hex2, hex1, hex0);

        // Test 3: Valores aleatorios
        value = 24'h123456;
        #100;
        $display("Valor: %h => HEX5-0: %h %h %h %h %h %h", 
                 value, hex5, hex4, hex3, hex2, hex1, hex0);

        value = 24'hABCDEF;
        #100;
        $display("Valor: %h => HEX5-0: %h %h %h %h %h %h", 
                 value, hex5, hex4, hex3, hex2, hex1, hex0);

        value = 24'hDEADBE;
        #100;
        $display("Valor: %h => HEX5-0: %h %h %h %h %h %h", 
                 value, hex5, hex4, hex3, hex2, hex1, hex0);

        // Test 4: Conteo incremental
        $display("=== Conteo incremental ===");
        for (int i = 0; i < 16; i++) begin
            value = i;
            #50;
            $display("Valor: %h", value);
        end

        $display("=== Simulación completada ===");
        $finish;
    end

endmodule

rv32i_mono/vcd/hex_display_6_tb.vcd
$date
	Tue Nov 25 16:24:48 2025
$end
$version
	Icarus Verilog
$end
$timescale
	1ps
$end
$scope module hex_display_6_tb $end
$var wire 7 ! hex5 [6:0] $end
$var wire 7 " hex4 [6:0] $end
$var wire 7 # hex3 [6:0] $end
$var wire 7 $ hex2 [6:0] $end
$var wire 7 % hex1 [6:0] $end
$var wire 7 & hex0 [6:0] $end
$var reg 24 ' value [23:0] $end
$scope module dut $end
$var wire 24 ( value [23:0] $end
$var wire 7 ) hex5 [6:0] $end
$var wire 7 * hex4 [6:0] $end
$var wire 7 + hex3 [6:0] $end
$var wire 7 , hex2 [6:0] $end
$var wire 7 - hex1 [6:0] $end
$var wire 7 . hex0 [6:0] $end
$scope module decoder0 $end
$var wire 4 / hex_value [3:0] $end
$var reg 7 0 seg [6:0] $end
$upscope $end
$scope module decoder1 $end
$var wire 4 1 hex_value [3:0] $end
$var reg 7 2 seg [6:0] $end
$upscope $end
$scope module decoder2 $end
$var wire 4 3 hex_value [3:0] $end
$var reg 7 4 seg [6:0] $end
$upscope $end
$scope module decoder3 $end
$var wire 4 5 hex_value [3:0] $end
$var reg 7 6 seg [6:0] $end
$upscope $end
$scope module decoder4 $end
$var wire 4 7 hex_value [3:0] $end
$var reg 7 8 seg [6:0] $end
$upscope $end
$scope module decoder5 $end
$var wire 4 9 hex_value [3:0] $end
$var reg 7 : seg [6:0] $end
$upscope $end
$upscope $end
$scope begin $ivl_for_loop0 $end
$var integer 32 ; i [31:0] $end
$upscope $end
$upscope $end
$enddefinitions $end
$comment Show the parameter values. $end
$dumpall
$end
#0
$dumpvars
b0 ;
b1000000 :
b0 9
b1000000 8
b0 7
b1000000 6
b0 5
b1000000 4
b0 3
b1000000 2
b0 1
b1000000 0
b0 /
b1000000 .
b1000000 -
b1000000 ,
b1000000 +
b1000000 *
b1000000 )
b0 (
b0 '
b1000000 &
b1000000 %
b1000000 $
b1000000 #
b1000000 "
b1000000 !
$end
#100000
b1110 &
b1110 .
b1110 0
b1110 %
b1110 -
b1110 2
b1110 $
b1110 ,
b1110 4
b1110 #
b1110 +
b1110 6
b1110 "
b1110 *
b1110 8
b1110 !
b1110 )
b1110 :
b1111 /
b1111 1
b1111 3
b1111 5
b1111 7
b1111 9
b111111111111111111111111 '
b111111111111111111111111 (
#200000
b10 &
b10 .
b10 0
b10010 %
b10010 -
b10010 2
b11001 $
b11001 ,
b11001 4
b110000 #
b110000 +
b110000 6
b100100 "
b100100 *
b100100 8
b1111001 !
b1111001 )
b1111001 :
b110 /
b101 1
b100 3
b11 5
b10 7
b1 9
b100100011010001010110 '
b100100011010001010110 (
#300000
b1110 &
b1110 .
b1110 0
b110 %
b110 -
b110 2
b100001 $
b100001 ,
b100001 4
b1000110 #
b1000110 +
b1000110 6
b11 "
b11 *
b11 8
b1000 !
b1000 )
b1000 :
b1111 /
b1110 1
b1101 3
b1100 5
b1011 7
b1010 9
b101010111100110111101111 '
b101010111100110111101111 (
#400000
b110 &
b110 .
b110 0
b11 %
b11 -
b11 2
b1000 #
b1000 +
b1000 6
b110 "
b110 *
b110 8
b100001 !
b100001 )
b100001 :
b1110 /
b1011 1
b1010 5
b1110 7
b1101 9
b110111101010110110111110 '
b110111101010110110111110 (
#500000
b1000000 &
b1000000 .
b1000000 0
b1000000 %
b1000000 -
b1000000 2
b1000000 $
b1000000 ,
b1000000 4
b1000000 #
b1000000 +
b1000000 6
b1000000 "
b1000000 *
b1000000 8
b1000000 !
b1000000 )
b1000000 :
b0 /
b0 1
b0 3
b0 5
b0 7
b0 9
b0 '
b0 (
#550000
b1111001 &
b1111001 .
b1111001 0
b1 /
b1 '
b1 (
b1 ;
#600000
b100100 &
b100100 .
b100100 0
b10 /
b10 '
b10 (
b10 ;
#650000
b110000 &
b110000 .
b110000 0
b11 /
b11 '
b11 (
b11 ;
#700000
b11001 &
b11001 .
b11001 0
b100 /
b100 '
b100 (
b100 ;
#750000
b10010 &
b10010 .
b10010 0
b101 /
b101 '
b101 (
b101 ;
#800000
b10 &
b10 .
b10 0
b110 /
b110 '
b110 (
b110 ;
#850000
b1111000 &
b1111000 .
b1111000 0
b111 /
b111 '
b111 (
b111 ;
#900000
b0 &
b0 .
b0 0
b1000 /
b1000 '
b1000 (
b1000 ;
#950000
b10000 &
b10000 .
b10000 0
b1001 /
b1001 '
b1001 (
b1001 ;
#1000000
b1000 &
b1000 .
b1000 0
b1010 /
b1010 '
b1010 (
b1010 ;
#1050000
b11 &
b11 .
b11 0
b1011 /
b1011 '
b1011 (
b1011 ;
#1100000
b1000110 &
b1000110 .
b1000110 0
b1100 /
b1100 '
b1100 (
b1100 ;
#1150000
b100001 &
b100001 .
b100001 0
b1101 /
b1101 '
b1101 (
b1101 ;
#1200000
b110 &
b110 .
b110 0
b1110 /
b1110 '
b1110 (
b1110 ;
#1250000
b1110 &
b1110 .
b1110 0
b1111 /
b1111 '
b1111 (
b1111 ;
#1300000
b10000 ;
