rv32i_mono/src/im.sv
module im (
    input  logic [31:0] addr,      // dirección desde el PC
    output logic [31:0] inst       // instrucción de 32 bits
);

    // Memoria de instrucciones - 256 palabras (1KB) - adecuado para FPGA
    (* ramstyle = "M10K" *) logic [31:0] mem [0:255];

    // Programa didáctico RV32I - Demostración completa de arquitectura
    initial begin
        integer i;
        for (i = 0; i < 256; i = i + 1) begin
            mem[i] = 32'h00000013; // NOP (ADDI x0, x0, 0)
        end
        
        // ===================================================================
        // PROGRAMA DIDÁCTICO: Calculadora de suma de números 1 al 5
        // ===================================================================
        // Registros usados:
        // x1 = contador (1, 2, 3, 4, 5)
        // x2 = límite (5)
        // x3 = acumulador de suma
        // x4 = dirección base de memoria
        // x5, x6, x7 = operaciones auxiliares
        // ===================================================================
        
        // --- INICIALIZACIÓN ---
        mem[0]  = 32'h00100093; // ADDI x1, x0, 1       | x1 = 1 (contador)
        mem[1]  = 32'h00600113; // ADDI x2, x0, 6       | x2 = 6 (límite, para loop hasta x1=5)
        mem[2]  = 32'h00000193; // ADDI x3, x0, 0       | x3 = 0 (suma)
        mem[3]  = 32'h00000213; // ADDI x4, x0, 0       | x4 = 0 (dir mem)
        
        // --- LOOP: Sumar números del 1 al 5 ---
        // [mem[4]] INICIO_LOOP:
        mem[4]  = 32'h001181B3; // ADD  x3, x3, x1      | suma += contador
        mem[5]  = 32'h00108093; // ADDI x1, x1, 1       | contador++ (CORREGIDO: rs1=x1, no x0)
        
        // --- Comparar si contador <= límite ---
        mem[6]  = 32'hFE20CCE3; // BLT  x1, x2, -8      | si x1<x2 salta a mem[4] (CORREGIDO: opcode 0x63)
        
        // --- GUARDAR resultado en memoria ---
        mem[7]  = 32'h00322023; // SW   x3, 0(x4)       | mem[0] = suma (debe ser 15)
        
        // --- OPERACIONES ARITMÉTICAS (demostración) ---
        mem[8]  = 32'h00A00293; // ADDI x5, x0, 10      | x5 = 10 = 0x0A
        mem[9]  = 32'h01400313; // ADDI x6, x0, 20      | x6 = 20 = 0x14
        mem[10] = 32'h006283B3; // ADD  x7, x5, x6      | x7 = 30 = 0x1E
        mem[11] = 32'h40628333; // SUB  x6, x5, x6      | x6 = -10 = 0xFFFFFFF6
        
        // --- OPERACIONES LÓGICAS ---
        mem[12] = 32'h0FF00293; // ADDI x5, x0, 255     | x5 = 0xFF
        mem[13] = 32'h0F000313; // ADDI x6, x0, 240     | x6 = 0xF0
        mem[14] = 32'h0062F3B3; // AND  x7, x5, x6      | x7 = 0xF0 operacion AND porque 0xFF & 0xF0 = 0xF0
        mem[15] = 32'h0062E3B3; // OR   x7, x5, x6      | x7 = 0xFF operacion OR porque 0xFF | 0xF0 = 0xFF
        mem[16] = 32'h0062C3B3; // XOR  x7, x5, x6      | x7 = 0x0F operacion XOR porque 0xFF ^ 0xF0 = 0x0F
        
        // --- DESPLAZAMIENTOS ---
        mem[17] = 32'h00800293; // ADDI x5, x0, 8       | x5 = 8
        mem[18] = 32'h00229293; // SLLI x5, x5, 2       | x5 = 32 (<<2) = 0x20
        mem[19] = 32'h0022D293; // SRLI x5, x5, 2       | x5 = 8  (>>2) = 0x08
        mem[20] = 32'hFF000313; // ADDI x6, x0, -16     | x6 = -16 = 0xFFFFFFF0
        mem[21] = 32'h40235313; // SRAI x6, x6, 2       | x6 = -4 (>>2 aritmético) = 0xFFFFFFFC
        
        // --- LOAD/STORE múltiple (usando mem[2]-mem[3] visibles en displays) ---
        mem[22] = 32'h00800213; // ADDI x4, x0, 8       | x4 = 8 (dirección mem[2])
        mem[23] = 32'h02A00293; // ADDI x5, x0, 42      | x5 = 42 = 0x2A
        mem[24] = 32'h00522023; // SW   x5, 0(x4)       | mem[2] = 42 = 0x2A
        mem[25] = 32'h00C00213; // ADDI x4, x0, 12      | x4 = 12 (dirección mem[3])
        mem[26] = 32'h05500293; // ADDI x5, x0, 85      | x5 = 85 = 0x55
        mem[27] = 32'h00522023; // SW   x5, 0(x4)       | mem[3] = 85 = 0x55
        mem[28] = 32'h00800213; // ADDI x4, x0, 8       | x4 = 8 (leer mem[2])
        mem[29] = 32'h00022303; // LW   x6, 0(x4)       | x6 = mem[2] = 42 = 0x2A
        mem[30] = 32'h00C00213; // ADDI x4, x0, 12      | x4 = 12 (leer mem[3])
        mem[31] = 32'h00022383; // LW   x7, 0(x4)       | x7 = mem[3] = 85 = 0x55
        
        // --- SALTOS CONDICIONALES ---
        mem[32] = 32'h00600293; // ADDI x5, x0, 6       | x5 = 6
        mem[33] = 32'h00600313; // ADDI x6, x0, 6       | x6 = 6
        mem[34] = 32'h00628463; // BEQ  x5, x6, +8      | salta si iguales → mem[36]
        mem[35] = 32'h00100293; // ADDI x5, x0, 1       | (NO ejecuta)
        mem[36] = 32'h00A00393; // ADDI x7, x0, 10      | x7 = 10
        
        // --- SALTO INCONDICIONAL (JAL) ---
        mem[37] = 32'h008000EF; // JAL  x1, +8          | Salta a mem[39], x1=PC+4
        mem[38] = 32'hDEADBEEF; // (dato - NO ejecuta)
        mem[39] = 32'h01400293; // ADDI x5, x0, 20      | x5 = 20
        
        // --- FIN DEL PROGRAMA ---
        mem[40] = 32'h00000013; // NOP
        mem[41] = 32'h00000013; // NOP
        mem[42] = 32'h00000013; // NOP (loop infinito aquí)
        
        // Instrucciones 43-255: NOPs
    end

    // Lectura asíncrona (combinacional)
    // addr está en bytes, pero necesitamos acceso por word (dividir entre 4)
    // addr[31:2] da el índice de la palabra
    assign inst = mem[addr[31:2]];

endmodule

rv32i_mono/tb/im_tb.sv
module im_tb;

    // Señales del testbench
    logic [31:0] addr;
    logic [31:0] inst;

    // Instancia del módulo
    im uut (
        .addr(addr),
        .inst(inst)
    );

    // Proceso de prueba
    initial begin
        $display("=== Testbench: Instruction Memory ===\n");

        // --- Prueba 1: Primera instrucción (ADDI x1, x0, 1) ---
        addr = 32'h00000000;
        #10;
        $display("Prueba 1 - addr=0x%08h: inst=0x%08h (esperado: 0x00100093 - ADDI x1,x0,1)", addr, inst);
        
        // --- Prueba 2: Segunda instrucción (ADDI x2, x0, 6) ---
        addr = 32'h00000004; // mem[1]
        #10;
        $display("Prueba 2 - addr=0x%08h: inst=0x%08h (esperado: 0x00600113 - ADDI x2,x0,6)", addr, inst);
        
        // --- Prueba 3: Inicio del loop (ADD x3, x3, x1) ---
        addr = 32'h00000010; // mem[4]
        #10;
        $display("Prueba 3 - addr=0x%08h: inst=0x%08h (esperado: 0x001181B3 - ADD x3,x3,x1)", addr, inst);
        
        // --- Prueba 4: BLT corregido ---
        addr = 32'h00000018; // mem[6]
        #10;
        $display("Prueba 4 - addr=0x%08h: inst=0x%08h (esperado: 0xFE20CCE3 - BLT x1,x2,-8)", addr, inst);
        
        // --- Prueba 5: Store result (SW x3, 0(x4)) ---
        addr = 32'h0000001C; // mem[7]
        #10;
        $display("Prueba 5 - addr=0x%08h: inst=0x%08h (esperado: 0x00322023 - SW x3,0(x4))", addr, inst);
        
        // --- Prueba 6: JAL instruction ---
        addr = 32'h00000094; // mem[37] = 0x94/4 = 37
        #10;
        $display("Prueba 6 - addr=0x%08h: inst=0x%08h (esperado: 0x008000EF - JAL x1,+8)", addr, inst);
        
        // --- Prueba 7: DEADBEEF (debe saltar sobre esta) ---
        addr = 32'h00000098; // mem[38]
        #10;
        $display("Prueba 7 - addr=0x%08h: inst=0x%08h (esperado: 0xDEADBEEF - dato invalido)", addr, inst);
        
        // --- Prueba 8: Después del salto ---
        addr = 32'h0000009C; // mem[39]
        #10;
        $display("Prueba 8 - addr=0x%08h: inst=0x%08h (esperado: 0x01400293 - ADDI x5,x0,20)", addr, inst);
        
        // --- Prueba 9: NOPs al final ---
        addr = 32'h000000A0; // mem[40]
        #10;
        $display("Prueba 9 - addr=0x%08h: inst=0x%08h (esperado: 0x00000013 - NOP)", addr, inst);
        
        // --- Prueba 10: Verificar que addr se divide entre 4 correctamente ---
        addr = 32'h00000002; // No alineado, pero debe leer mem[0]
        #10;
        $display("\nPrueba 10 - addr=0x%08h (no alineado): inst=0x%08h (debe leer mem[0])", addr, inst);
        
        addr = 32'h00000006; // No alineado, debe leer mem[1]
        #10;
        $display("Prueba 10b - addr=0x%08h (no alineado): inst=0x%08h (debe leer mem[1])", addr, inst);

        $display("\n=== Testbench completado ===");
        $finish;
    end

    // Generar archivo VCD para WaveTrace
    initial begin
        $dumpfile("vcd/im_tb.vcd");
        $dumpvars(0, im_tb);
    end

endmodule

rv32i_mono/vcd/im_tb.vcd
$date
	Thu Nov 27 09:57:38 2025
$end
$version
	Icarus Verilog
$end
$timescale
	1s
$end
$scope module im_tb $end
$var wire 32 ! inst [31:0] $end
$var reg 32 " addr [31:0] $end
$scope module uut $end
$var wire 32 # addr [31:0] $end
$var wire 32 $ inst [31:0] $end
$scope begin $unm_blk_3 $end
$var integer 32 % i [31:0] $end
$upscope $end
$upscope $end
$upscope $end
$enddefinitions $end
$comment Show the parameter values. $end
$dumpall
$end
#0
$dumpvars
b100000000 %
b100000000000010010011 $
b0 #
b0 "
b100000000000010010011 !
$end
#10
b11000000000000100010011 !
b11000000000000100010011 $
b100 "
b100 #
#20
b100011000000110110011 !
b100011000000110110011 $
b10000 "
b10000 #
#30
b11111110001000001100110011100011 !
b11111110001000001100110011100011 $
b11000 "
b11000 #
#40
b1100100010000000100011 !
b1100100010000000100011 $
b11100 "
b11100 #
#50
b100000000000000011101111 !
b100000000000000011101111 $
b10010100 "
b10010100 #
#60
b11011110101011011011111011101111 !
b11011110101011011011111011101111 $
b10011000 "
b10011000 #
#70
b1010000000000001010010011 !
b1010000000000001010010011 $
b10011100 "
b10011100 #
#80
b10011 !
b10011 $
b10100000 "
b10100000 #
#90
b100000000000010010011 !
b100000000000010010011 $
b10 "
b10 #
#100
b11000000000000100010011 !
b11000000000000100010011 $
b110 "
b110 #
