rv32i_mono/src/ru.sv
module ru(
  input logic clk, //Reloj
  input logic [4:0] rs1, //Registro fuente 1
  input logic [4:0] rs2, //Registro fuente 2
  input logic [4:0] rd, //Registro destino
  input logic [31:0] DataWr, //Dato a escribir
  input logic RUWr, //Señal de control para escribir en el banco de registros
  output logic [31:0] RU_rs1, //Dato del registro fuente 1
  output logic [31:0] RU_rs2, //Dato del registro fuente 2
  
  // Puertos de debug individuales (como en segmentado)
  output logic [31:0] debug_x1,
  output logic [31:0] debug_x2,
  output logic [31:0] debug_x3,
  output logic [31:0] debug_x4,
  output logic [31:0] debug_x5,
  output logic [31:0] debug_x6,
  output logic [31:0] debug_x7
  );

  //En risc V la arquitectura usa 32 registros de 32 bits, se puede ver como una matriz de 32 registros x 32 bits

  (* ramstyle = "logic" *) logic [31:0] RU [0:31]; //Banco de registros (debe usar LUTs, no M10K)
  initial begin
    integer i;
    for(i = 0; i<32; i=i+1)begin
      RU[i] = 32'b0; //Inicializar todos los registros a 0
    end
    // Para demostración didáctica, todos los registros empiezan en 0
    // En un sistema real, x2 (sp) se inicializaría como stack pointer
    // RU[2] = 32'h00000400; // 1 KiB = 1024 bytes (comentado para didáctica)
  end

  //Lectura asincronica
  assign RU_rs1 = RU[rs1]; //Lectura del registro fuente 1
  assign RU_rs2 = RU[rs2]; //Lectura del registro fuente 2

  //Escritura sincronica
  always_ff @(posedge clk) begin
    if (RUWr && (rd != 0)) begin //Si la señal de control es alta y el registro destino no es 0
      RU[rd] <= DataWr; //Escritura del dato en el registro destino
    end
  end

  // Exportar registros individuales para debug (reduce lógica combinacional)
  assign debug_x1 = RU[1];
  assign debug_x2 = RU[2];
  assign debug_x3 = RU[3];
  assign debug_x4 = RU[4];
  assign debug_x5 = RU[5];
  assign debug_x6 = RU[6];
  assign debug_x7 = RU[7];

endmodule

rv32i_mono/tb/ru_tb.sv
`timescale 1ns / 1ps

module ru_tb;
  // Señales internas
  logic clk;
  logic [4:0] rs1, rs2, rd;
  logic [31:0] DataWr;
  logic RUWr;
  logic [31:0] RU_rs1, RU_rs2;

  // Instancia del módulo RU
  ru uut (
    .clk(clk),
    .rs1(rs1),
    .rs2(rs2),
    .rd(rd),
    .DataWr(DataWr),
    .RUWr(RUWr),
    .RU_rs1(RU_rs1),
    .RU_rs2(RU_rs2)
  );

  // Generación de reloj
  initial begin
    clk = 0;
    forever #5 clk = ~clk;
  end

  initial begin
    $dumpfile("vcd/ru_tb.vcd");
    $dumpvars(0, ru_tb);
    $display("=================================================================");
    $display("            TESTBENCH PARA REGISTER UNIT (RU)");
    $display("=================================================================\n");

    // Inicializar señales
    rs1 = 5'd0; rs2 = 5'd0; rd = 5'd0; DataWr = 32'd0; RUWr = 1'b0;
    #10;

    $display("\n--- Prueba 1: Lectura asíncrona de x0 y x2 (Stack Pointer) ---");
    rs1 = 5'd0; rs2 = 5'd2;
    #2;
    $display("x0 = 0x%h (debe ser 0x00000000)", RU_rs1);
    $display("x2 = 0x%h (debe ser 0xFFFFFFFF)", RU_rs2);

    $display("\n--- Prueba 2: Escritura síncrona en x5 ---");
    @(posedge clk);
    rd = 5'd5; DataWr = 32'hA5A5A5A5; RUWr = 1'b1;
    $display("Escribiendo 0xA5A5A5A5 en x5...");
    @(posedge clk);
    RUWr = 1'b0; rs1 = 5'd5;
    #2;
    $display("x5 = 0x%h (debe ser 0xA5A5A5A5)", RU_rs1);

    $display("\n--- Prueba 3: Protección de x0 (intento de escritura) ---");
    @(posedge clk);
    rd = 5'd0; DataWr = 32'hDEADBEEF; RUWr = 1'b1;
    $display("Intentando escribir 0xDEADBEEF en x0...");
    @(posedge clk);
    RUWr = 1'b0; rs1 = 5'd0;
    #2;
    $display("x0 = 0x%h (debe permanecer 0x00000000)", RU_rs1);

    $display("\n--- Prueba 4: Escrituras múltiples y lectura simultánea ---");
    @(posedge clk);
    rd = 5'd10; DataWr = 32'h12345678; RUWr = 1'b1;
    @(posedge clk);
    rd = 5'd15; DataWr = 32'h87654321; RUWr = 1'b1;
    @(posedge clk);
    @(posedge clk);
    RUWr = 1'b0;
    rs1 = 5'd10; rs2 = 5'd15;
    #2;
    $display("x10 = 0x%h (debe ser 0x12345678)", RU_rs1);
    $display("x15 = 0x%h (debe ser 0x87654321)", RU_rs2);

    $display("\n--- Prueba 5: Sobrescritura de un registro ---");
    @(posedge clk);
    rd = 5'd5; DataWr = 32'h0000FFFF; RUWr = 1'b1;
    $display("Sobrescribiendo x5 con 0x0000FFFF...");
    @(posedge clk);
    RUWr = 1'b0; rs1 = 5'd5;
    #2;
    $display("x5 = 0x%h (debe ser 0x0000FFFF)", RU_rs1);

    $display("\n--- Prueba 6: Lectura asíncrona de múltiples registros ---");
    rs1 = 5'd10; rs2 = 5'd5;
    #2;
    $display("Lectura simultánea: x10=0x%h, x5=0x%h", RU_rs1, RU_rs2);

    $display("\n=================================================================");
    $display("                     FIN DE SIMULACIÓN");
    $display("=================================================================");
    #20 $finish;
  end
endmodule

rv32i_mono/vcd/ru_tb.vcd
$date
	Tue Dec 02 11:28:54 2025
$end
$version
	Icarus Verilog
$end
$timescale
	1ps
$end
$scope module ru_tb $end
$var wire 32 ! RU_rs2 [31:0] $end
$var wire 32 " RU_rs1 [31:0] $end
$var reg 32 # DataWr [31:0] $end
$var reg 1 $ RUWr $end
$var reg 1 % clk $end
$var reg 5 & rd [4:0] $end
$var reg 5 ' rs1 [4:0] $end
$var reg 5 ( rs2 [4:0] $end
$scope module uut $end
$var wire 32 ) DataWr [31:0] $end
$var wire 1 $ RUWr $end
$var wire 32 * RU_rs1 [31:0] $end
$var wire 32 + RU_rs2 [31:0] $end
$var wire 1 % clk $end
$var wire 32 , debug_x1 [31:0] $end
$var wire 32 - debug_x2 [31:0] $end
$var wire 32 . debug_x3 [31:0] $end
$var wire 32 / debug_x4 [31:0] $end
$var wire 32 0 debug_x5 [31:0] $end
$var wire 32 1 debug_x6 [31:0] $end
$var wire 32 2 debug_x7 [31:0] $end
$var wire 5 3 rd [4:0] $end
$var wire 5 4 rs1 [4:0] $end
$var wire 5 5 rs2 [4:0] $end
$scope begin $unm_blk_3 $end
$var integer 32 6 i [31:0] $end
$upscope $end
$upscope $end
$upscope $end
$enddefinitions $end
$comment Show the parameter values. $end
$dumpall
$end
#0
$dumpvars
b100000 6
b0 5
b0 4
b0 3
b0 2
b0 1
b0 0
b0 /
b0 .
b0 -
b0 ,
b0 +
b0 *
b0 )
b0 (
b0 '
b0 &
0%
0$
b0 #
b0 "
b0 !
$end
#5000
1%
#10000
0%
b10 (
b10 5
#15000
b10100101101001011010010110100101 0
1$
b10100101101001011010010110100101 #
b10100101101001011010010110100101 )
b101 &
b101 3
1%
#20000
0%
#25000
b10100101101001011010010110100101 "
b10100101101001011010010110100101 *
b101 '
b101 4
0$
1%
#30000
0%
#35000
1$
b11011110101011011011111011101111 #
b11011110101011011011111011101111 )
b0 &
b0 3
1%
#40000
0%
#45000
b0 "
b0 *
b0 '
b0 4
0$
1%
#50000
0%
#55000
1$
b10010001101000101011001111000 #
b10010001101000101011001111000 )
b1010 &
b1010 3
1%
#60000
0%
#65000
b10000111011001010100001100100001 #
b10000111011001010100001100100001 )
b1111 &
b1111 3
1%
#70000
0%
#75000
1%
#80000
0%
#85000
b10000111011001010100001100100001 !
b10000111011001010100001100100001 +
b1111 (
b1111 5
b10010001101000101011001111000 "
b10010001101000101011001111000 *
b1010 '
b1010 4
0$
1%
#90000
0%
#95000
b1111111111111111 0
1$
b1111111111111111 #
b1111111111111111 )
b101 &
b101 3
1%
#100000
0%
#105000
b1111111111111111 "
b1111111111111111 *
b101 '
b101 4
0$
1%
#107000
b1111111111111111 !
b1111111111111111 +
b101 (
b101 5
b10010001101000101011001111000 "
b10010001101000101011001111000 *
b1010 '
b1010 4
